{
	"schemaVersion": 1,
	"id": "rocketriding",
	"version": "${version}",
	"name": "RocketRiding",
	"description": "Ride firework rockets",
	"authors": [
		"ThePotatoArchivist"
	],
	"contact": {
		"homepage": "https://modrinth.com/mod/",
		"sources": "https://github.com/ThePotatoArchivist/RocketRiding"
	},
	"license": "MIT",
	"icon": "assets/rocketriding/icon.png",
	"environment": "*",
	"entrypoints": {
		"main": [
			"archives.tater.rocketriding.RocketRiding"
		],
		"client": [
			"archives.tater.rocketriding.RocketRidingClient"
		]
	},
	"accessWidener": "rocketriding.accesswidener",
	"mixins": [
		"rocketriding.mixins.json",
		{
			"config": "rocketriding.client.mixins.json",
			"environment": "client"
		}
	],
	"depends": {
		"fabricloader": ">=0.16.14",
		"minecraft": "~1.21.1",
		"java": ">=21",
		"fabric-api": "*"
	},
	"suggests": {
		"another-mod": "*"
	}
}